tcp_send_first_segment_last/__init__.py
tcp_send_first_segment_last/send.py
tcp_send_first_segment_last/lib/IP_Datagram.py
tcp_send_first_segment_last/lib/TCP_Flags.py
tcp_send_first_segment_last/lib/TCP_Segment.py
tcp_send_first_segment_last/lib/__init__.py
tcp_send_first_segment_last/lib/checksum.py
tcp_send_first_segment_last/lib/disable_auto_rst.py
tcp_send_first_segment_last/lib/socket_reader.py
tcp_send_first_segment_last-0.0.5.dist-info/METADATA
tcp_send_first_segment_last-0.0.5.dist-info/WHEEL
tcp_send_first_segment_last-0.0.5.dist-info/RECORD
