Metadata-Version: 2.3
Name: tcp_send_first_segment_last
Version: 0.0.5
Summary: Send the first TCP segment last for large payloads
Project-URL: Homepage, https://github.com/johnnyodonnell/python-tcp-send-first-segment-last
Project-URL: Issues, https://github.com/johnnyodonnell/python-tcp-send-first-segment-last/issues
Author-email: Johnny O'Donnell <odonnell_johnny@yahoo.com>
Classifier: License :: OSI Approved :: MIT License
Classifier: Operating System :: OS Independent
Classifier: Programming Language :: Python :: 3
Requires-Python: >=3.8
